ofpost/__init__.py
ofpost/__main__.py
ofpost/lib.py
ofpost/options.py
openfoampost-1.1.7.dist-info/licenses/LICENSE.txt
openfoampost-1.1.7.dist-info/METADATA
openfoampost-1.1.7.dist-info/WHEEL
openfoampost-1.1.7.dist-info/entry_points.txt
openfoampost-1.1.7.dist-info/top_level.txt
openfoampost-1.1.7.dist-info/RECORD
