Metadata-Version: 2.4
Name: OpenFOAMPost
Version: 1.1.7
Summary: A powerful tool to to post-process OpenFOAM simulations.
Home-page: https://github.com/TheBusyDev/OpenFOAMPost
Author: TheBusyDev
Author-email: pietro.busy@gmail.com
License: MIT
Requires-Python: >= 3.10, < 4
License-File: LICENSE.txt
Requires-Dist: build==1.2.2.post1
Requires-Dist: matplotlib==3.10.3
Requires-Dist: numpy==2.2.5
Requires-Dist: pandas==2.2.3
Requires-Dist: pyvista==0.45.2
Dynamic: author
Dynamic: author-email
Dynamic: description
Dynamic: description-content-type
Dynamic: home-page
Dynamic: license
Dynamic: license-file
Dynamic: requires-dist
Dynamic: requires-python
Dynamic: summary
